[{"action": "red", "bg": "white", "a1": "blue", "a2": "green", "bg1": "white", "bg2": "white", "reward": 0}, {"action": "green", "bg": "white", "a1": "green", "a2": "red", "bg1": "white", "bg2": "white", "reward": 1}, {"action": "red", "bg": "white", "a1": "red", "a2": "green", "bg1": "white", "bg2": "white", "reward": 0}, {"action": "red", "bg": "white", "a1": "green", "a2": "red", "bg1": "white", "bg2": "white", "reward": 0}, {"action": "green", "bg": "white", "a1": "red", "a2": "red", "bg1": "white", "bg2": "white", "reward": 1}, {"action": "green", "bg": "white", "a1": "red", "a2": "green", "bg1": "white", "bg2": "white", "reward": 1}, {"action": "green", "bg": "black", "a1": "green", "a2": "green", "bg1": "white", "bg2": "white", "reward": 1}, {"action": "green", "bg": "black", "a1": "green", "a2": "green", "bg1": "white", "bg2": "black", "reward": 1}, {"action": "green", "bg": "white", "a1": "green", "a2": "green", "bg1": "black", "bg2": "black", "reward": 1}, {"action": "green", "bg": "white", "a1": "green", "a2": "green", "bg1": "black", "bg2": "white", "reward": 1}, {"action": "green", "bg": "black", "a1": "green", "a2": "green", "bg1": "white", "bg2": "white", "reward": 1}, {"action": "green", "bg": "black", "a1": "green", "a2": "green", "bg1": "white", "bg2": "black", "reward": 1}, {"action": "blue", "bg": "white", "a1": "green", "a2": "green", "bg1": "black", "bg2": "black", "reward": 0}, {"action": "red", "bg": "white", "a1": "green", "a2": "blue", "bg1": "black", "bg2": "white", "reward": 0}, {"action": "green", "bg": "white", "a1": "blue", "a2": "red", "bg1": "white", "bg2": "white", "reward": 1}, {"action": "blue", "bg": "black", "a1": "red", "a2": "green", "bg1": "white", "bg2": "white", "reward": 0}, {"action": "blue", "bg": "black", "a1": "green", "a2": "blue", "bg1": "white", "bg2": "black", "reward": 0}, {"action": "green", "bg": "black", "a1": "blue", "a2": "blue", "bg1": "black", "bg2": "black", "reward": 1}, {"action": "green", "bg": "black", "a1": "blue", "a2": "green", "bg1": "black", "bg2": "black", "reward": 1}, {"action": "green", "bg": "black", "a1": "green", "a2": "green", "bg1": "black", "bg2": "black", "reward": 1}, {"action": "green", "bg": "black", "a1": "green", "a2": "green", "bg1": "black", "bg2": "black", "reward": 1}, {"action": "green", "bg": "black", "a1": "green", "a2": "green", "bg1": "black", "bg2": "black", "reward": 1}, {"action": "green", "bg": "white", "a1": "green", "a2": "green", "bg1": "black", "bg2": "black", "reward": 1}, {"action": "blue", "bg": "black", "a1": "green", "a2": "green", "bg1": "black", "bg2": "white", "reward": 0}, {"action": "red", "bg": "black", "a1": "green", "a2": "blue", "bg1": "white", "bg2": "black", "reward": 0}, {"action": "red", "bg": "black", "a1": "blue", "a2": "red", "bg1": "black", "bg2": "black", "reward": 0}, {"action": "green", "bg": "black", "a1": "red", "a2": "red", "bg1": "black", "bg2": "black", "reward": 1}, {"action": "green", "bg": "black", "a1": "red", "a2": "green", "bg1": "black", "bg2": "black", "reward": 1}, {"action": "green", "bg": "black", "a1": "green", "a2": "green", "bg1": "black", "bg2": "black", "reward": 1}, {"action": "green", "bg": "black", "a1": "green", "a2": "green", "bg1": "black", "bg2": "black", "reward": 1}, {"action": "green", "bg": "black", "a1": "green", "a2": "green", "bg1": "black", "bg2": "black", "reward": 1}, {"action": "green", "bg": "black", "a1": "green", "a2": "green", "bg1": "black", "bg2": "black", "reward": 1}, {"action": "green", "bg": "black", "a1": "green", "a2": "green", "bg1": "black", "bg2": "black", "reward": 1}, {"action": "green", "bg": "black", "a1": "green", "a2": "green", "bg1": "black", "bg2": "black", "reward": 1}, {"action": "green", "bg": "black", "a1": "green", "a2": "green", "bg1": "black", "bg2": "black", "reward": 1}, {"action": "green", "bg": "black", "a1": "green", "a2": "green", "bg1": "black", "bg2": "black", "reward": 1}, {"action": "green", "bg": "black", "a1": "green", "a2": "green", "bg1": "black", "bg2": "black", "reward": 1}, {"action": "green", "bg": "black", "a1": "green", "a2": "green", "bg1": "black", "bg2": "black", "reward": 1}, {"action": "green", "bg": "black", "a1": "green", "a2": "green", "bg1": "black", "bg2": "black", "reward": 1}, {"action": "green", "bg": "white", "a1": "green", "a2": "green", "bg1": "black", "bg2": "black", "reward": 1}, {"action": "green", "bg": "white", "a1": "green", "a2": "green", "bg1": "black", "bg2": "white", "reward": 1}, {"action": "green", "bg": "black", "a1": "green", "a2": "green", "bg1": "white", "bg2": "white", "reward": 1}, {"action": "green", "bg": "black", "a1": "green", "a2": "green", "bg1": "white", "bg2": "black", "reward": 1}, {"action": "green", "bg": "black", "a1": "green", "a2": "green", "bg1": "black", "bg2": "black", "reward": 1}, {"action": "green", "bg": "black", "a1": "green", "a2": "green", "bg1": "black", "bg2": "black", "reward": 1}, {"action": "green", "bg": "black", "a1": "green", "a2": "green", "bg1": "black", "bg2": "black", "reward": 1}, {"action": "green", "bg": "black", "a1": "green", "a2": "green", "bg1": "black", "bg2": "black", "reward": 1}, {"action": "green", "bg": "white", "a1": "green", "a2": "green", "bg1": "black", "bg2": "black", "reward": 1}, {"action": "green", "bg": "white", "a1": "green", "a2": "green", "bg1": "black", "bg2": "white", "reward": 1}, {"action": "green", "bg": "white", "a1": "green", "a2": "green", "bg1": "white", "bg2": "white", "reward": 1}, {"action": "green", "bg": "white", "a1": "green", "a2": "green", "bg1": "white", "bg2": "white", "reward": 1}, {"action": "green", "bg": "white", "a1": "green", "a2": "green", "bg1": "white", "bg2": "white", "reward": 1}, {"action": "green", "bg": "white", "a1": "green", "a2": "green", "bg1": "white", "bg2": "white", "reward": 1}, {"action": "green", "bg": "white", "a1": "green", "a2": "green", "bg1": "white", "bg2": "white", "reward": 1}, {"action": "green", "bg": "white", "a1": "green", "a2": "green", "bg1": "white", "bg2": "white", "reward": 1}, {"action": "green", "bg": "white", "a1": "green", "a2": "green", "bg1": "white", "bg2": "white", "reward": 1}, {"action": "green", "bg": "white", "a1": "green", "a2": "green", "bg1": "white", "bg2": "white", "reward": 1}, {"action": "green", "bg": "white", "a1": "green", "a2": "green", "bg1": "white", "bg2": "white", "reward": 1}, {"action": "green", "bg": "white", "a1": "green", "a2": "green", "bg1": "white", "bg2": "white", "reward": 1}, {"action": "green", "bg": "black", "a1": "green", "a2": "green", "bg1": "white", "bg2": "white", "reward": 1}, {"action": "green", "bg": "black", "a1": "green", "a2": "green", "bg1": "white", "bg2": "black", "reward": 1}, {"action": "green", "bg": "black", "a1": "green", "a2": "green", "bg1": "black", "bg2": "black", "reward": 1}, {"action": "green", "bg": "black", "a1": "green", "a2": "green", "bg1": "black", "bg2": "black", "reward": 1}, {"action": "green", "bg": "black", "a1": "green", "a2": "green", "bg1": "black", "bg2": "black", "reward": 1}, {"action": "green", "bg": "black", "a1": "green", "a2": "green", "bg1": "black", "bg2": "black", "reward": 1}, {"action": "green", "bg": "white", "a1": "green", "a2": "green", "bg1": "black", "bg2": "black", "reward": 1}, {"action": "green", "bg": "white", "a1": "green", "a2": "green", "bg1": "black", "bg2": "white", "reward": 1}, {"action": "green", "bg": "white", "a1": "green", "a2": "green", "bg1": "white", "bg2": "white", "reward": 1}, {"action": "red", "bg": "black", "a1": "blue", "a2": "red", "bg1": "black", "bg2": "black", "reward": 0}, {"action": "red", "bg": "black", "a1": "red", "a2": "red", "bg1": "black", "bg2": "black", "reward": 0}, {"action": "red", "bg": "black", "a1": "red", "a2": "red", "bg1": "black", "bg2": "black", "reward": 0}, {"action": "red", "bg": "black", "a1": "red", "a2": "red", "bg1": "black", "bg2": "black", "reward": 0}, {"action": "red", "bg": "white", "a1": "red", "a2": "red", "bg1": "black", "bg2": "black", "reward": 0}, {"action": "red", "bg": "white", "a1": "red", "a2": "red", "bg1": "black", "bg2": "white", "reward": 0}, {"action": "red", "bg": "white", "a1": "red", "a2": "red", "bg1": "white", "bg2": "white", "reward": 0}, {"action": "green", "bg": "white", "a1": "red", "a2": "red", "bg1": "white", "bg2": "white", "reward": 1}, {"action": "green", "bg": "white", "a1": "red", "a2": "green", "bg1": "white", "bg2": "white", "reward": 1}, {"action": "green", "bg": "white", "a1": "green", "a2": "green", "bg1": "white", "bg2": "white", "reward": 1}, {"action": "green", "bg": "white", "a1": "green", "a2": "green", "bg1": "white", "bg2": "white", "reward": 1}, {"action": "green", "bg": "white", "a1": "green", "a2": "green", "bg1": "white", "bg2": "white", "reward": 1}, {"action": "green", "bg": "white", "a1": "green", "a2": "green", "bg1": "white", "bg2": "white", "reward": 1}, {"action": "green", "bg": "black", "a1": "green", "a2": "green", "bg1": "white", "bg2": "white", "reward": 1}, {"action": "green", "bg": "white", "a1": "green", "a2": "green", "bg1": "white", "bg2": "black", "reward": 1}, {"action": "green", "bg": "white", "a1": "green", "a2": "green", "bg1": "black", "bg2": "white", "reward": 1}, {"action": "green", "bg": "white", "a1": "green", "a2": "green", "bg1": "white", "bg2": "white", "reward": 1}, {"action": "green", "bg": "white", "a1": "green", "a2": "green", "bg1": "white", "bg2": "white", "reward": 1}, {"action": "green", "bg": "white", "a1": "green", "a2": "green", "bg1": "white", "bg2": "white", "reward": 1}, {"action": "green", "bg": "white", "a1": "green", "a2": "green", "bg1": "white", "bg2": "white", "reward": 1}, {"action": "green", "bg": "black", "a1": "green", "a2": "green", "bg1": "white", "bg2": "white", "reward": 1}, {"action": "green", "bg": "black", "a1": "green", "a2": "green", "bg1": "white", "bg2": "black", "reward": 1}, {"action": "green", "bg": "black", "a1": "green", "a2": "green", "bg1": "black", "bg2": "black", "reward": 1}, {"action": "green", "bg": "white", "a1": "green", "a2": "green", "bg1": "black", "bg2": "black", "reward": 1}, {"action": "green", "bg": "white", "a1": "green", "a2": "green", "bg1": "black", "bg2": "white", "reward": 1}, {"action": "green", "bg": "white", "a1": "green", "a2": "green", "bg1": "white", "bg2": "white", "reward": 1}, {"action": "green", "bg": "white", "a1": "green", "a2": "green", "bg1": "white", "bg2": "white", "reward": 1}, {"action": "green", "bg": "white", "a1": "green", "a2": "green", "bg1": "white", "bg2": "white", "reward": 1}, {"action": "green", "bg": "black", "a1": "green", "a2": "green", "bg1": "white", "bg2": "white", "reward": 1}, {"action": "green", "bg": "black", "a1": "green", "a2": "green", "bg1": "white", "bg2": "black", "reward": 1}, {"action": "green", "bg": "white", "a1": "green", "a2": "green", "bg1": "black", "bg2": "black", "reward": 1}, {"action": "green", "bg": "black", "a1": "green", "a2": "green", "bg1": "black", "bg2": "white", "reward": 1}, {"action": "green", "bg": "white", "a1": "green", "a2": "green", "bg1": "white", "bg2": "black", "reward": 1}, {"action": "green", "bg": "white", "a1": "green", "a2": "green", "bg1": "black", "bg2": "white", "reward": 1}, {"action": "green", "bg": "black", "a1": "green", "a2": "green", "bg1": "white", "bg2": "white", "reward": 1}, {"action": "green", "bg": "white", "a1": "green", "a2": "green", "bg1": "white", "bg2": "black", "reward": 1}, {"action": "green", "bg": "white", "a1": "green", "a2": "green", "bg1": "black", "bg2": "white", "reward": 1}, {"action": "green", "bg": "white", "a1": "green", "a2": "green", "bg1": "white", "bg2": "white", "reward": 1}, {"action": "green", "bg": "black", "a1": "green", "a2": "green", "bg1": "white", "bg2": "white", "reward": 1}, {"action": "green", "bg": "black", "a1": "green", "a2": "green", "bg1": "white", "bg2": "black", "reward": 1}, {"action": "green", "bg": "black", "a1": "green", "a2": "green", "bg1": "black", "bg2": "black", "reward": 1}, {"action": "green", "bg": "black", "a1": "green", "a2": "green", "bg1": "black", "bg2": "black", "reward": 1}, {"action": "green", "bg": "black", "a1": "green", "a2": "green", "bg1": "black", "bg2": "black", "reward": 1}, {"action": "green", "bg": "black", "a1": "green", "a2": "green", "bg1": "black", "bg2": "black", "reward": 1}, {"action": "green", "bg": "black", "a1": "green", "a2": "green", "bg1": "black", "bg2": "black", "reward": 1}, {"action": "green", "bg": "white", "a1": "green", "a2": "green", "bg1": "black", "bg2": "black", "reward": 1}, {"action": "green", "bg": "black", "a1": "green", "a2": "green", "bg1": "black", "bg2": "white", "reward": 1}, {"action": "green", "bg": "black", "a1": "green", "a2": "green", "bg1": "white", "bg2": "black", "reward": 1}, {"action": "green", "bg": "white", "a1": "green", "a2": "green", "bg1": "black", "bg2": "black", "reward": 1}, {"action": "green", "bg": "white", "a1": "green", "a2": "green", "bg1": "black", "bg2": "white", "reward": 1}, {"action": "green", "bg": "black", "a1": "green", "a2": "green", "bg1": "white", "bg2": "white", "reward": 1}, {"action": "green", "bg": "white", "a1": "green", "a2": "green", "bg1": "white", "bg2": "black", "reward": 1}, {"action": "green", "bg": "white", "a1": "green", "a2": "green", "bg1": "black", "bg2": "white", "reward": 1}, {"action": "green", "bg": "white", "a1": "green", "a2": "green", "bg1": "white", "bg2": "white", "reward": 1}, {"action": "green", "bg": "white", "a1": "green", "a2": "green", "bg1": "white", "bg2": "white", "reward": 1}, {"action": "green", "bg": "white", "a1": "green", "a2": "green", "bg1": "white", "bg2": "white", "reward": 1}, {"action": "green", "bg": "white", "a1": "green", "a2": "green", "bg1": "white", "bg2": "white", "reward": 1}, {"action": "green", "bg": "white", "a1": "green", "a2": "green", "bg1": "white", "bg2": "white", "reward": 1}, {"action": "green", "bg": "white", "a1": "green", "a2": "green", "bg1": "white", "bg2": "white", "reward": 1}, {"action": "green", "bg": "white", "a1": "green", "a2": "green", "bg1": "white", "bg2": "white", "reward": 1}, {"action": "green", "bg": "white", "a1": "green", "a2": "green", "bg1": "white", "bg2": "white", "reward": 1}, {"action": "green", "bg": "white", "a1": "green", "a2": "green", "bg1": "white", "bg2": "white", "reward": 1}, {"action": "green", "bg": "white", "a1": "green", "a2": "green", "bg1": "white", "bg2": "white", "reward": 1}, {"action": "green", "bg": "white", "a1": "green", "a2": "green", "bg1": "white", "bg2": "white", "reward": 1}, {"action": "green", "bg": "white", "a1": "green", "a2": "green", "bg1": "white", "bg2": "white", "reward": 1}, {"action": "green", "bg": "black", "a1": "green", "a2": "green", "bg1": "white", "bg2": "white", "reward": 1}, {"action": "green", "bg": "black", "a1": "green", "a2": "green", "bg1": "white", "bg2": "black", "reward": 1}, {"action": "green", "bg": "black", "a1": "green", "a2": "green", "bg1": "black", "bg2": "black", "reward": 1}, {"action": "green", "bg": "black", "a1": "green", "a2": "green", "bg1": "black", "bg2": "black", "reward": 1}, {"action": "green", "bg": "black", "a1": "green", "a2": "green", "bg1": "black", "bg2": "black", "reward": 1}, {"action": "green", "bg": "white", "a1": "green", "a2": "green", "bg1": "black", "bg2": "black", "reward": 1}, {"action": "green", "bg": "white", "a1": "green", "a2": "green", "bg1": "black", "bg2": "white", "reward": 1}, {"action": "green", "bg": "white", "a1": "green", "a2": "green", "bg1": "white", "bg2": "white", "reward": 1}, {"action": "green", "bg": "black", "a1": "green", "a2": "green", "bg1": "white", "bg2": "white", "reward": 1}, {"action": "green", "bg": "black", "a1": "green", "a2": "green", "bg1": "white", "bg2": "black", "reward": 1}, {"action": "green", "bg": "black", "a1": "green", "a2": "green", "bg1": "black", "bg2": "black", "reward": 1}, {"action": "green", "bg": "black", "a1": "green", "a2": "green", "bg1": "black", "bg2": "black", "reward": 1}, {"action": "green", "bg": "black", "a1": "green", "a2": "green", "bg1": "black", "bg2": "black", "reward": 1}, {"action": "green", "bg": "white", "a1": "green", "a2": "green", "bg1": "black", "bg2": "black", "reward": 1}, {"action": "green", "bg": "white", "a1": "green", "a2": "green", "bg1": "black", "bg2": "white", "reward": 1}, {"action": "green", "bg": "white", "a1": "green", "a2": "green", "bg1": "white", "bg2": "white", "reward": 1}, {"action": "green", "bg": "white", "a1": "green", "a2": "green", "bg1": "white", "bg2": "white", "reward": 1}, {"action": "green", "bg": "white", "a1": "green", "a2": "green", "bg1": "white", "bg2": "white", "reward": 1}, {"action": "green", "bg": "black", "a1": "green", "a2": "green", "bg1": "white", "bg2": "white", "reward": 1}, {"action": "green", "bg": "black", "a1": "green", "a2": "green", "bg1": "white", "bg2": "black", "reward": 1}, {"action": "red", "bg": "black", "a1": "green", "a2": "green", "bg1": "black", "bg2": "black", "reward": 0}, {"action": "green", "bg": "white", "a1": "green", "a2": "red", "bg1": "black", "bg2": "black", "reward": 1}, {"action": "green", "bg": "white", "a1": "red", "a2": "green", "bg1": "black", "bg2": "white", "reward": 1}, {"action": "green", "bg": "black", "a1": "green", "a2": "green", "bg1": "white", "bg2": "white", "reward": 1}, {"action": "green", "bg": "black", "a1": "green", "a2": "green", "bg1": "white", "bg2": "black", "reward": 1}, {"action": "green", "bg": "black", "a1": "green", "a2": "green", "bg1": "black", "bg2": "black", "reward": 1}, {"action": "green", "bg": "black", "a1": "green", "a2": "green", "bg1": "black", "bg2": "black", "reward": 1}, {"action": "green", "bg": "black", "a1": "green", "a2": "green", "bg1": "black", "bg2": "black", "reward": 1}, {"action": "red", "bg": "white", "a1": "red", "a2": "red", "bg1": "white", "bg2": "white", "reward": 0}, {"action": "blue", "bg": "white", "a1": "red", "a2": "red", "bg1": "white", "bg2": "white", "reward": 0}, {"action": "green", "bg": "white", "a1": "red", "a2": "blue", "bg1": "white", "bg2": "white", "reward": 1}, {"action": "green", "bg": "white", "a1": "blue", "a2": "green", "bg1": "white", "bg2": "white", "reward": 1}, {"action": "green", "bg": "white", "a1": "green", "a2": "green", "bg1": "white", "bg2": "white", "reward": 1}, {"action": "green", "bg": "white", "a1": "green", "a2": "green", "bg1": "white", "bg2": "white", "reward": 1}, {"action": "green", "bg": "white", "a1": "green", "a2": "green", "bg1": "white", "bg2": "white", "reward": 1}, {"action": "green", "bg": "white", "a1": "green", "a2": "green", "bg1": "white", "bg2": "white", "reward": 1}, {"action": "green", "bg": "white", "a1": "green", "a2": "green", "bg1": "white", "bg2": "white", "reward": 1}, {"action": "green", "bg": "black", "a1": "green", "a2": "green", "bg1": "white", "bg2": "white", "reward": 1}, {"action": "green", "bg": "black", "a1": "green", "a2": "green", "bg1": "white", "bg2": "black", "reward": 1}, {"action": "green", "bg": "white", "a1": "green", "a2": "green", "bg1": "black", "bg2": "black", "reward": 1}, {"action": "green", "bg": "white", "a1": "green", "a2": "green", "bg1": "black", "bg2": "white", "reward": 1}, {"action": "green", "bg": "black", "a1": "green", "a2": "green", "bg1": "white", "bg2": "white", "reward": 1}, {"action": "green", "bg": "black", "a1": "green", "a2": "green", "bg1": "white", "bg2": "black", "reward": 1}, {"action": "green", "bg": "black", "a1": "green", "a2": "green", "bg1": "black", "bg2": "black", "reward": 1}, {"action": "green", "bg": "black", "a1": "green", "a2": "green", "bg1": "black", "bg2": "black", "reward": 1}, {"action": "green", "bg": "black", "a1": "green", "a2": "green", "bg1": "black", "bg2": "black", "reward": 1}, {"action": "green", "bg": "white", "a1": "green", "a2": "green", "bg1": "black", "bg2": "black", "reward": 1}, {"action": "green", "bg": "white", "a1": "green", "a2": "green", "bg1": "black", "bg2": "white", "reward": 1}, {"action": "green", "bg": "white", "a1": "green", "a2": "green", "bg1": "white", "bg2": "white", "reward": 1}, {"action": "green", "bg": "white", "a1": "green", "a2": "green", "bg1": "white", "bg2": "white", "reward": 1}, {"action": "green", "bg": "black", "a1": "green", "a2": "green", "bg1": "white", "bg2": "white", "reward": 1}, {"action": "green", "bg": "black", "a1": "green", "a2": "green", "bg1": "white", "bg2": "black", "reward": 1}, {"action": "green", "bg": "black", "a1": "green", "a2": "green", "bg1": "black", "bg2": "black", "reward": 1}, {"action": "green", "bg": "black", "a1": "green", "a2": "green", "bg1": "black", "bg2": "black", "reward": 1}, {"action": "green", "bg": "black", "a1": "green", "a2": "green", "bg1": "black", "bg2": "black", "reward": 1}, {"action": "green", "bg": "black", "a1": "green", "a2": "green", "bg1": "black", "bg2": "black", "reward": 1}, {"action": "green", "bg": "black", "a1": "green", "a2": "green", "bg1": "black", "bg2": "black", "reward": 1}, {"action": "green", "bg": "black", "a1": "green", "a2": "green", "bg1": "black", "bg2": "black", "reward": 1}, {"action": "green", "bg": "black", "a1": "green", "a2": "green", "bg1": "black", "bg2": "black", "reward": 1}, {"action": "green", "bg": "black", "a1": "green", "a2": "green", "bg1": "black", "bg2": "black", "reward": 1}, {"action": "green", "bg": "white", "a1": "green", "a2": "green", "bg1": "black", "bg2": "black", "reward": 1}, {"action": "green", "bg": "white", "a1": "green", "a2": "green", "bg1": "black", "bg2": "white", "reward": 1}, {"action": "green", "bg": "white", "a1": "green", "a2": "green", "bg1": "white", "bg2": "white", "reward": 1}, {"action": "green", "bg": "white", "a1": "green", "a2": "green", "bg1": "white", "bg2": "white", "reward": 1}, {"action": "green", "bg": "white", "a1": "green", "a2": "green", "bg1": "white", "bg2": "white", "reward": 1}, {"action": "green", "bg": "white", "a1": "green", "a2": "green", "bg1": "white", "bg2": "white", "reward": 1}, {"action": "green", "bg": "black", "a1": "green", "a2": "green", "bg1": "white", "bg2": "white", "reward": 1}, {"action": "green", "bg": "white", "a1": "green", "a2": "green", "bg1": "white", "bg2": "black", "reward": 1}, {"action": "green", "bg": "white", "a1": "green", "a2": "green", "bg1": "black", "bg2": "white", "reward": 1}, {"action": "green", "bg": "white", "a1": "green", "a2": "green", "bg1": "white", "bg2": "white", "reward": 1}, {"action": "green", "bg": "white", "a1": "green", "a2": "green", "bg1": "white", "bg2": "white", "reward": 1}, {"action": "green", "bg": "white", "a1": "green", "a2": "green", "bg1": "white", "bg2": "white", "reward": 1}, {"action": "green", "bg": "white", "a1": "green", "a2": "green", "bg1": "white", "bg2": "white", "reward": 1}, {"action": "green", "bg": "black", "a1": "green", "a2": "green", "bg1": "white", "bg2": "white", "reward": 1}, {"action": "green", "bg": "white", "a1": "green", "a2": "green", "bg1": "white", "bg2": "black", "reward": 1}, {"action": "green", "bg": "white", "a1": "green", "a2": "green", "bg1": "black", "bg2": "white", "reward": 1}, {"action": "green", "bg": "white", "a1": "green", "a2": "green", "bg1": "white", "bg2": "white", "reward": 1}, {"action": "green", "bg": "white", "a1": "green", "a2": "green", "bg1": "white", "bg2": "white", "reward": 1}, {"action": "green", "bg": "white", "a1": "green", "a2": "green", "bg1": "white", "bg2": "white", "reward": 1}, {"action": "green", "bg": "black", "a1": "green", "a2": "green", "bg1": "white", "bg2": "white", "reward": 1}, {"action": "green", "bg": "black", "a1": "green", "a2": "green", "bg1": "white", "bg2": "black", "reward": 1}, {"action": "green", "bg": "black", "a1": "green", "a2": "green", "bg1": "black", "bg2": "black", "reward": 1}, {"action": "green", "bg": "black", "a1": "green", "a2": "green", "bg1": "black", "bg2": "black", "reward": 1}, {"action": "green", "bg": "black", "a1": "green", "a2": "green", "bg1": "black", "bg2": "black", "reward": 1}, {"action": "green", "bg": "black", "a1": "green", "a2": "green", "bg1": "black", "bg2": "black", "reward": 1}, {"action": "green", "bg": "black", "a1": "green", "a2": "green", "bg1": "black", "bg2": "black", "reward": 1}, {"action": "green", "bg": "black", "a1": "green", "a2": "green", "bg1": "black", "bg2": "black", "reward": 1}, {"action": "green", "bg": "black", "a1": "green", "a2": "green", "bg1": "black", "bg2": "black", "reward": 1}, {"action": "green", "bg": "black", "a1": "green", "a2": "green", "bg1": "black", "bg2": "black", "reward": 1}, {"action": "green", "bg": "white", "a1": "green", "a2": "green", "bg1": "black", "bg2": "black", "reward": 1}, {"action": "green", "bg": "white", "a1": "green", "a2": "green", "bg1": "black", "bg2": "white", "reward": 1}, {"action": "green", "bg": "black", "a1": "green", "a2": "green", "bg1": "white", "bg2": "white", "reward": 1}, {"action": "green", "bg": "black", "a1": "green", "a2": "green", "bg1": "white", "bg2": "black", "reward": 1}, {"action": "green", "bg": "black", "a1": "green", "a2": "green", "bg1": "black", "bg2": "black", "reward": 1}, {"action": "green", "bg": "white", "a1": "green", "a2": "green", "bg1": "black", "bg2": "black", "reward": 1}, {"action": "green", "bg": "white", "a1": "green", "a2": "green", "bg1": "black", "bg2": "white", "reward": 1}, {"action": "green", "bg": "white", "a1": "green", "a2": "green", "bg1": "white", "bg2": "white", "reward": 1}, {"action": "green", "bg": "white", "a1": "green", "a2": "green", "bg1": "white", "bg2": "white", "reward": 1}, {"action": "green", "bg": "white", "a1": "green", "a2": "green", "bg1": "white", "bg2": "white", "reward": 1}, {"action": "green", "bg": "white", "a1": "green", "a2": "green", "bg1": "white", "bg2": "white", "reward": 1}, {"action": "green", "bg": "white", "a1": "green", "a2": "green", "bg1": "white", "bg2": "white", "reward": 1}, {"action": "green", "bg": "black", "a1": "green", "a2": "green", "bg1": "white", "bg2": "white", "reward": 1}, {"action": "green", "bg": "white", "a1": "green", "a2": "green", "bg1": "white", "bg2": "black", "reward": 1}, {"action": "green", "bg": "white", "a1": "green", "a2": "green", "bg1": "black", "bg2": "white", "reward": 1}, {"action": "green", "bg": "white", "a1": "green", "a2": "green", "bg1": "white", "bg2": "white", "reward": 1}, {"action": "green", "bg": "white", "a1": "green", "a2": "green", "bg1": "white", "bg2": "white", "reward": 1}, {"action": "green", "bg": "black", "a1": "green", "a2": "green", "bg1": "white", "bg2": "white", "reward": 1}, {"action": "green", "bg": "black", "a1": "green", "a2": "green", "bg1": "white", "bg2": "black", "reward": 1}, {"action": "green", "bg": "black", "a1": "green", "a2": "green", "bg1": "black", "bg2": "black", "reward": 1}, {"action": "green", "bg": "black", "a1": "green", "a2": "green", "bg1": "black", "bg2": "black", "reward": 1}, {"action": "green", "bg": "black", "a1": "green", "a2": "green", "bg1": "black", "bg2": "black", "reward": 1}, {"action": "green", "bg": "black", "a1": "green", "a2": "green", "bg1": "black", "bg2": "black", "reward": 1}, {"action": "green", "bg": "black", "a1": "green", "a2": "green", "bg1": "black", "bg2": "black", "reward": 1}, {"action": "green", "bg": "white", "a1": "green", "a2": "green", "bg1": "black", "bg2": "black", "reward": 1}, {"action": "green", "bg": "white", "a1": "green", "a2": "green", "bg1": "black", "bg2": "white", "reward": 1}, {"action": "green", "bg": "white", "a1": "green", "a2": "green", "bg1": "white", "bg2": "white", "reward": 1}, {"action": "green", "bg": "white", "a1": "green", "a2": "green", "bg1": "white", "bg2": "white", "reward": 1}, {"action": "green", "bg": "white", "a1": "green", "a2": "green", "bg1": "white", "bg2": "white", "reward": 1}, {"action": "green", "bg": "white", "a1": "green", "a2": "green", "bg1": "white", "bg2": "white", "reward": 1}, {"action": "green", "bg": "black", "a1": "green", "a2": "green", "bg1": "white", "bg2": "white", "reward": 1}, {"action": "green", "bg": "white", "a1": "green", "a2": "green", "bg1": "white", "bg2": "black", "reward": 1}, {"action": "green", "bg": "black", "a1": "green", "a2": "green", "bg1": "black", "bg2": "white", "reward": 1}, {"action": "green", "bg": "white", "a1": "green", "a2": "green", "bg1": "white", "bg2": "black", "reward": 1}, {"action": "green", "bg": "white", "a1": "green", "a2": "green", "bg1": "black", "bg2": "white", "reward": 1}, {"action": "green", "bg": "white", "a1": "green", "a2": "green", "bg1": "white", "bg2": "white", "reward": 1}, {"action": "green", "bg": "white", "a1": "green", "a2": "green", "bg1": "white", "bg2": "white", "reward": 1}, {"action": "green", "bg": "black", "a1": "green", "a2": "green", "bg1": "white", "bg2": "white", "reward": 1}, {"action": "green", "bg": "black", "a1": "green", "a2": "green", "bg1": "white", "bg2": "black", "reward": 1}, {"action": "green", "bg": "black", "a1": "green", "a2": "green", "bg1": "black", "bg2": "black", "reward": 1}, {"action": "green", "bg": "black", "a1": "green", "a2": "green", "bg1": "black", "bg2": "black", "reward": 1}, {"action": "green", "bg": "black", "a1": "green", "a2": "green", "bg1": "black", "bg2": "black", "reward": 1}, {"action": "green", "bg": "black", "a1": "green", "a2": "green", "bg1": "black", "bg2": "black", "reward": 1}, {"action": "green", "bg": "black", "a1": "green", "a2": "green", "bg1": "black", "bg2": "black", "reward": 1}, {"action": "green", "bg": "black", "a1": "green", "a2": "green", "bg1": "black", "bg2": "black", "reward": 1}, {"action": "green", "bg": "white", "a1": "green", "a2": "green", "bg1": "black", "bg2": "black", "reward": 1}, {"action": "green", "bg": "white", "a1": "green", "a2": "green", "bg1": "black", "bg2": "white", "reward": 1}, {"action": "green", "bg": "white", "a1": "green", "a2": "green", "bg1": "white", "bg2": "white", "reward": 1}, {"action": "green", "bg": "white", "a1": "green", "a2": "green", "bg1": "white", "bg2": "white", "reward": 1}, {"action": "green", "bg": "black", "a1": "green", "a2": "green", "bg1": "white", "bg2": "white", "reward": 1}, {"action": "green", "bg": "black", "a1": "green", "a2": "green", "bg1": "white", "bg2": "black", "reward": 1}, {"action": "green", "bg": "black", "a1": "green", "a2": "green", "bg1": "black", "bg2": "black", "reward": 1}, {"action": "green", "bg": "black", "a1": "green", "a2": "green", "bg1": "black", "bg2": "black", "reward": 1}, {"action": "green", "bg": "black", "a1": "green", "a2": "green", "bg1": "black", "bg2": "black", "reward": 1}, {"action": "green", "bg": "black", "a1": "green", "a2": "green", "bg1": "black", "bg2": "black", "reward": 1}, {"action": "green", "bg": "black", "a1": "green", "a2": "green", "bg1": "black", "bg2": "black", "reward": 1}, {"action": "green", "bg": "black", "a1": "green", "a2": "green", "bg1": "black", "bg2": "black", "reward": 1}, {"action": "green", "bg": "black", "a1": "green", "a2": "green", "bg1": "black", "bg2": "black", "reward": 1}, {"action": "green", "bg": "black", "a1": "green", "a2": "green", "bg1": "black", "bg2": "black", "reward": 1}, {"action": "green", "bg": "black", "a1": "green", "a2": "green", "bg1": "black", "bg2": "black", "reward": 1}, {"action": "green", "bg": "white", "a1": "green", "a2": "green", "bg1": "black", "bg2": "black", "reward": 1}, {"action": "green", "bg": "white", "a1": "green", "a2": "green", "bg1": "black", "bg2": "white", "reward": 1}, {"action": "green", "bg": "white", "a1": "green", "a2": "green", "bg1": "white", "bg2": "white", "reward": 1}]